LICENSE
MANIFEST.in
README.md
setup.cfg
setup.py
py_ttr.egg-info/PKG-INFO
py_ttr.egg-info/SOURCES.txt
py_ttr.egg-info/dependency_links.txt
py_ttr.egg-info/entry_points.txt
py_ttr.egg-info/requires.txt
py_ttr.egg-info/top_level.txt
ttr/__init__.py
ttr/ttr.py
ttr/plugins/__init__.py
ttr/plugins/data/__init__.py
ttr/plugins/data/csv_loader.py
ttr/plugins/data/xlsx_loader.py
ttr/plugins/data/yaml_loader.py
ttr/plugins/models/__init__.py
ttr/plugins/models/yangson_model_loader.py
ttr/plugins/processors/__init__.py
ttr/plugins/processors/filtering.py
ttr/plugins/processors/multitemplate_processor.py
ttr/plugins/processors/templates_split.py
ttr/plugins/renderers/__init__.py
ttr/plugins/renderers/jinja2_renderer.py
ttr/plugins/returners/__init__.py
ttr/plugins/returners/file_returner.py
ttr/plugins/returners/self_returner.py
ttr/plugins/returners/terminal_returner.py
ttr/plugins/templates/__init__.py
ttr/plugins/templates/base_template_loader.py
ttr/plugins/templates/dir_template_loader.py
ttr/plugins/templates/file_template_loader.py
ttr/plugins/templates/ttr_template_loader.py
ttr/plugins/templates/xlsx_template_loader.py
ttr/plugins/validate/__init__.py
ttr/plugins/validate/validate_yangson.py
ttr/templates/simple/interface.cisco_ios.txt
ttr/templates/simple/interface.cisco_nxos.txt
ttr/utils/__init__.py
ttr/utils/cli.py