Metadata-Version: 2.1
Name: py-ttr
Version: 0.4.0
Summary: Template Text Renderer
Home-page: http://github.com/dmulyalin/ttr
Author: Denis Mulyalin
Author-email: d.mulyalin@gmail.com
License: UNKNOWN
Platform: UNKNOWN
Classifier: Topic :: Utilities
Classifier: Programming Language :: Python :: 3.6
Classifier: Programming Language :: Python :: 3.7
Classifier: License :: OSI Approved :: MIT License
Classifier: Operating System :: OS Independent
Requires-Python: >=3.6
